mete0r_monkeypatchbuildout
