Metadata-Version: 1.1
Name: mete0r.monkeypatchbuildout
Version: 0.0.1
Summary: monkeypatch buildout for some reason
Home-page: https://github.com/mete0r/monkeypatchbuildout
Author: mete0r
Author-email: mete0r@sarangbang.or.kr
License: GNU Affero General Public License v3 or later (AGPLv3+)
Keywords: buildout
Platform: UNKNOWN
Classifier: Development Status :: 1 - Planning
Classifier: License :: OSI Approved :: GNU Affero General Public License v3 or later (AGPLv3+)
Classifier: Programming Language :: Python :: 2.7
